clickup/__init__.py
clickup/client.py
clickup-0.0.10.dist-info/LICENSE
clickup-0.0.10.dist-info/METADATA
clickup-0.0.10.dist-info/WHEEL
clickup-0.0.10.dist-info/top_level.txt
clickup-0.0.10.dist-info/RECORD
