Metadata-Version: 2.1
Name: clickup
Version: 0.0.10
Summary: A Python library for the ClickUp API
Home-page: https://github.com/secdevopsai/clickup
Author: Ronald Eddings
Author-email: ron@secdevops.ai
License: UNKNOWN
Platform: UNKNOWN
Classifier: Programming Language :: Python :: 3
Classifier: License :: OSI Approved :: MIT License
Classifier: Operating System :: OS Independent
